{
  "provider_schemas": {
    "huaweicloud/huaweicloud": {
      "resource_schemas": {
        "huaweicloud_dds_instance_flavor_update": {
          "block": {
            "attributes": {
              "id": {
                "type": "string",
                "computed": true
              },
              "instance_id": {
                "type": "string",
                "required": true
              },
              "region": {
                "type": "string",
                "computed": true
              },
              "target_id": {
                "type": "string",
                "optional": true
              },
              "target_ids": {
                "type": [
                  "set",
                  "string"
                ],
                "optional": true
              },
              "target_spec_code": {
                "type": "string",
                "required": true
              },
              "target_type": {
                "type": "string",
                "optional": true
              }
            }
          },
          "product": {
            "short": "DDS",
            "name": "Document Database Service",
            "catalog": "Databases",
            "name_cn": "文档数据库服务",
            "catalog_cn": "数据库"
          }
        }
      }
    }
  }
}
