{
  "provider_schemas": {
    "huaweicloud/huaweicloud": {
      "data_source_schemas": {
        "huaweicloud_aom_cloud_service_authorizations": {
          "block": {
            "attributes": {
              "authorizations": {
                "type": [
                  "list",
                  [
                    "object",
                    {
                      "role_name": [
                        "list",
                        "string"
                      ],
                      "service": "string",
                      "status": "bool"
                    }
                  ]
                ],
                "description": "Indicates the authorizations list.",
                "computed": true
              },
              "id": {
                "type": "string",
                "computed": true
              },
              "region": {
                "type": "string",
                "description": "Specifies the region in which to query the resource. If omitted, the provider-level region will be used.",
                "computed": true
              }
            }
          },
          "product": {
            "short": "AOM",
            "name": "Application Operations Management",
            "catalog": "Management & Governance",
            "name_cn": "应用运维管理",
            "catalog_cn": "管理与监管"
          }
        }
      }
    }
  }
}
