{
  "provider_schemas": {
    "huaweicloud/huaweicloud": {
      "data_source_schemas": {
        "huaweicloud_apig_instance_tags": {
          "block": {
            "attributes": {
              "id": {
                "type": "string",
                "computed": true
              },
              "instance_id": {
                "type": "string",
                "description": "The ID of the dedicated instance to which the tags belong.",
                "optional": true
              },
              "region": {
                "type": "string",
                "description": "The region in which to query the instance tags.",
                "computed": true
              },
              "tags": {
                "type": [
                  "list",
                  [
                    "object",
                    {
                      "key": "string",
                      "value": "string"
                    }
                  ]
                ],
                "description": "The tags that belong to the dedicated instance.",
                "computed": true
              }
            }
          },
          "product": {
            "short": "APIG",
            "name": "API Gateway",
            "catalog": "Middleware",
            "name_cn": "API网关",
            "catalog_cn": "应用中间件"
          }
        }
      }
    }
  }
}
