{
  "provider_schemas": {
    "huaweicloud/huaweicloud": {
      "data_source_schemas": {
        "huaweicloud_codearts_pipeline_modify_histories": {
          "block": {
            "attributes": {
              "histories": {
                "type": [
                  "list",
                  [
                    "object",
                    {
                      "create_time": "number",
                      "creator_name": "string",
                      "creator_nick_name": "string",
                      "modify_type": "string"
                    }
                  ]
                ],
                "description": "Indicates the history list.",
                "computed": true
              },
              "id": {
                "type": "string",
                "computed": true
              },
              "pipeline_id": {
                "type": "string",
                "description": "Specifies the pipeline ID.",
                "required": true
              },
              "project_id": {
                "type": "string",
                "description": "Specifies the CodeArts project ID.",
                "required": true
              },
              "region": {
                "type": "string",
                "computed": true
              }
            }
          }
        }
      }
    }
  }
}
