{
  "provider_schemas": {
    "huaweicloud/huaweicloud": {
      "data_source_schemas": {
        "huaweicloud_dc_hosted_connects": {
          "block": {
            "attributes": {
              "hosted_connect_id": {
                "type": [
                  "list",
                  "string"
                ],
                "description": "Specifies the hosted connect IDs.",
                "optional": true
              },
              "hosted_connects": {
                "type": [
                  "list",
                  [
                    "object",
                    {
                      "apply_time": "string",
                      "bandwidth": "number",
                      "create_time": "string",
                      "description": "string",
                      "hosting_id": "string",
                      "id": "string",
                      "location": "string",
                      "name": "string",
                      "peer_location": "string",
                      "port_type": "string",
                      "provider": "string",
                      "provider_status": "string",
                      "status": "string",
                      "type": "string",
                      "vlan": "number"
                    }
                  ]
                ],
                "description": "Indicates the list of hosted connects.",
                "computed": true
              },
              "hosting_id": {
                "type": [
                  "list",
                  "string"
                ],
                "description": "Specifies the hosting direct connect IDs to which the hosted connects belong.",
                "optional": true
              },
              "id": {
                "type": "string",
                "computed": true
              },
              "name": {
                "type": [
                  "list",
                  "string"
                ],
                "description": "Specifies the hosted connect names.",
                "optional": true
              },
              "region": {
                "type": "string",
                "description": "Specifies the region in which to query the resource. If omitted, the provider-level region will be used.",
                "computed": true
              },
              "sort_dir": {
                "type": [
                  "list",
                  "string"
                ],
                "description": "Specifies the sorting order of returned results.",
                "optional": true
              },
              "sort_key": {
                "type": "string",
                "description": "Specifies the sorting field.",
                "optional": true
              }
            }
          },
          "product": {
            "short": "DC",
            "name": "Direct Connect",
            "catalog": "Networking",
            "name_cn": "云专线",
            "catalog_cn": "网络"
          }
        }
      }
    }
  }
}
